BatchGPT/Cleaner.py
BatchGPT/Prompt.py
BatchGPT/example01.py
BatchGPT-0.0.4.dist-info/LICENSE
BatchGPT-0.0.4.dist-info/METADATA
BatchGPT-0.0.4.dist-info/WHEEL
BatchGPT-0.0.4.dist-info/top_level.txt
BatchGPT-0.0.4.dist-info/RECORD
