Metadata-Version: 2.1
Name: BatchGPT
Version: 0.0.4
Summary: A package for handling ChatGPT prompt for large datasets
Author-email: Amirmahdi Mohammadi <mohamadi.mahdi.6@gmail.com>
Project-URL: Homepage, https://github.com/am-mohammadi/BatchGPT.git
Classifier: Programming Language :: Python :: 3
Classifier: License :: OSI Approved :: MIT License
Classifier: Operating System :: OS Independent
Requires-Python: >=3.7
License-File: LICENSE
